ovoscope/__init__.py
ovoscope/version.py
ovoscope-0.7.2.dist-info/METADATA
ovoscope-0.7.2.dist-info/WHEEL
ovoscope-0.7.2.dist-info/top_level.txt
ovoscope-0.7.2.dist-info/RECORD
