Metadata-Version: 2.1
Name: ovoscope
Version: 0.7.2
Summary: End-to-end test framework for OpenVoiceOS skills
Home-page: https://github.com/TigreGotico/ovoscope
Author: JarbasAI
Author-email: jarbasai@mailfence.com
License: Apache-2.0
Classifier: Programming Language :: Python :: 3
Classifier: License :: OSI Approved :: Apache Software License
Classifier: Operating System :: OS Independent
Classifier: Intended Audience :: Developers
Classifier: Topic :: Software Development :: Testing
Requires-Python: >=3.10
Requires-Dist: ovos-core>=2.0.4a2
